recept/__init__.py
recept/__main__.py
recept/apps.py
recept/cli.py
recept/config.py
recept/docker.py
recept/env.py
recept/errors.py
recept/python.py
recept/termui.py
recept/utils.py
recept/version.py
recept/tests/__init__.py
recept/tests/env/__init__.py
recept/tests/env/test_env.py
recept/tests/env/test_to_env_mixin.py
recept-0.0.12.dist-info/LICENSE
recept-0.0.12.dist-info/METADATA
recept-0.0.12.dist-info/WHEEL
recept-0.0.12.dist-info/entry_points.txt
recept-0.0.12.dist-info/top_level.txt
recept-0.0.12.dist-info/RECORD
