Metadata-Version: 2.1
Name: recept
Version: 0.0.12
Summary: Recipe runner and a recipes functions library.
Home-page: https://github.com/alefnula/recept
Author: Viktor Kerkez
Author-email: alefnula@gmail.com
Maintainer: Viktor Kerkez
Maintainer-email: alefnula@gmail.com
License: Apache-2.0
Platform: Windows
Platform: POSIX
Platform: MacOS
Classifier: Programming Language :: Python :: 3
Classifier: Programming Language :: Python :: 3.7
Classifier: License :: OSI Approved :: Apache Software License
Classifier: Operating System :: OS Independent
Classifier: Intended Audience :: Developers
Requires-Dist: click (==7.0)
Requires-Dist: sh (==1.12.14)
Requires-Dist: tsh (==0.0.1)
